haruka_parser/__init__.py
haruka_parser/extract.py
haruka_parser/html_text.py
haruka_parser/latex_processing.py
haruka_parser/line_processing.py
haruka_parser/meta_processing.py
haruka_parser/readablity_go.py
haruka_parser/readablity_lxml.py
haruka_parser/time_formatter.py
haruka_parser/tree_cleaning.py
haruka_parser/tree_processing.py
haruka_parser/utils.py
haruka_parser/dictionary/Blocks.txt
haruka_parser/dictionary/banned_selectors.txt
haruka_parser/dictionary/boilerplate_words.txt
haruka_parser/dictionary/highlightjs.py
haruka_parser/dictionary/language.py
haruka_parser/dictionary/latex_words.txt
haruka_parser/dictionary/public_suffix_list.txt
haruka_parser/filter/__init__.py
haruka_parser/filter/_import_utils.py
haruka_parser/filter/base_filter.py
haruka_parser/filter/c4_filters.py
haruka_parser/filter/data.py
haruka_parser/filter/fineweb_quality_filter.py
haruka_parser/filter/gopher_quality_filter.py
haruka_parser/filter/gopher_repetition_filter.py
haruka_parser/filter/text.py
haruka_parser/filter/typeshelper.py
haruka_parser/filter/url_filter.py
haruka_parser/filter/word_tokenizers.py
haruka_parser/filter/assets/banned_subwords.txt
haruka_parser/filter/assets/banned_words.txt
haruka_parser/filter/assets/soft_banned_words.txt
haruka_parser/filter/assets/adult/domains.gz
haruka_parser/filter/assets/adult/expressions
haruka_parser/filter/assets/adult/urls
haruka_parser/filter/assets/adult/usage
haruka_parser/filter/assets/nltk_data/tokenizers/punkt/README
haruka_parser/filter/assets/nltk_data/tokenizers/punkt/czech.pickle
haruka_parser/filter/assets/nltk_data/tokenizers/punkt/danish.pickle
haruka_parser/filter/assets/nltk_data/tokenizers/punkt/dutch.pickle
haruka_parser/filter/assets/nltk_data/tokenizers/punkt/english.pickle
haruka_parser/filter/assets/nltk_data/tokenizers/punkt/estonian.pickle
haruka_parser/filter/assets/nltk_data/tokenizers/punkt/finnish.pickle
haruka_parser/filter/assets/nltk_data/tokenizers/punkt/french.pickle
haruka_parser-1.1.1.dist-info/METADATA
haruka_parser-1.1.1.dist-info/WHEEL
haruka_parser-1.1.1.dist-info/top_level.txt
haruka_parser-1.1.1.dist-info/RECORD
