Metadata-Version: 2.4
Name: haruka_parser
Version: 1.1.1
Summary: A simple HTML Parser
Home-page: https://github.com/prnake/haruka-parser
Author: papersnake
Author-email: prnake@gmail.com
Classifier: Programming Language :: Python :: 3
Classifier: License :: OSI Approved :: MIT License
Classifier: Operating System :: OS Independent
Classifier: Topic :: Text Processing
Classifier: Topic :: Text Processing :: Markup :: HTML
Classifier: Topic :: Utilities
Requires-Dist: py_asciimath
Requires-Dist: inscriptis==2.5.0
Requires-Dist: tabulate
Requires-Dist: numpy
Requires-Dist: resiliparse
Requires-Dist: ftfy
Requires-Dist: faust-cchardet
Requires-Dist: lxml
Requires-Dist: lxml_html_clean
Requires-Dist: courlan
Requires-Dist: charset_normalizer
Requires-Dist: trafilatura
Requires-Dist: tldextract
Requires-Dist: pyahocorasick
Requires-Dist: nltk
Requires-Dist: uniseg
Requires-Dist: pyyaml
Provides-Extra: dev
Requires-Dist: fasttext; extra == "dev"
Dynamic: author
Dynamic: author-email
Dynamic: classifier
Dynamic: description
Dynamic: description-content-type
Dynamic: home-page
Dynamic: provides-extra
Dynamic: requires-dist
Dynamic: summary
